Workbook

Sheet Colaboradores
A1: Codigo | B1: Nombre | C1: Correo | D1: CURP | E1: JefeCodigo | F1: Area | G1: Departamento | H1: Categoria | I1: DiasAsignados | J1: FechaIngreso | K1: EsRRHH | L1: Puesto
A2: 10001 | B2: NANCY JANET GOMEZ RUIZ | C2: ngomez@cafepuntadelcielo.co | D2: GORN8008076X7 | E2: ANA LILIA MENDOZA TORRES | F2: FINANZAS | G2: CUENTAS POR COBRAR | H2: ADMINISTRATIVO | I2: 52 | J2: 26/02/2008 | L2: =IF($B2="","",IFERROR(_xlfn.XLOOKUP(_xlfn.TEXTJOIN(" ",TRUE,_xlfn._xlws.SORT(_xlfn.TEXTSPLIT(TRIM(UPPER($B2))," ",,TRUE),1,1,TRUE)),puestos!$C$2:$C$324,puestos!$B$2:$B$324),"SIN PUESTO")) -> COORDINADOR CUENTAS POR COBRAR
A3: 10002 | B3: MANUEL JAVIER VILLEDA MORENO | D3: VIMM691203AW6 | E3: NEIDY MARTINEZ MARTINEZ | F3: MANUFACTURA | G3: ARQUITECTURA | H3: OPERATIVO | I3: 58 | J3: 19/10/2009 | L3: =IF($B3="","",IFERROR(_xlfn.XLOOKUP(_xlfn.TEXTJOIN(" ",TRUE,_xlfn._xlws.SORT(_xlfn.TEXTSPLIT(TRIM(UPPER($B3))," ",,TRUE),1,1,TRUE)),puestos!$C$2:$C$324,puestos!$B$2:$B$324),"SIN PUESTO")) -> AUXILIAR DE MANTENIMIENTO
A4: 10003 | B4: JOSE FELIX FLORES ROJAS | D4: FORF650530RA3 | E4: NEIDY MARTINEZ MARTINEZ | F4: LOGISTICA & OPERACIONES | G4: ARQUITECTURA | H4: OPERATIVO | I4: 48 | J4: 16/06/2011 | L4: =IF($B4="","",IFERROR(_xlfn.XLOOKUP(_xlfn.TEXTJOIN(" ",TRUE,_xlfn._xlws.SORT(_xlfn.TEXTSPLIT(TRIM(UPPER($B4))," ",,TRUE),1,1,TRUE)),puestos!$C$2:$C$324,puestos!$B$2:$B$324),"SIN PUESTO")) -> AUXILIAR DE INFRAESTRUCTURA
A5: 10004 | B5: ELIA CRESCENCIO ESQUIVEL | C5: ecrescencio@cafepuntadelcielo.co | D5: CEEE7905108E7 | E5: EDGAR ALVAREZ RIOS | F5: FINANZAS | G5: CONTABILIDAD | H5: ADMINISTRATIVO | I5: 70 | J5: 12/10/2012 | L5: =IF($B5="","",IFERROR(_xlfn.XLOOKUP(_xlfn.TEXTJOIN(" ",TRUE,_xlfn._xlws.SORT(_xlfn.TEXTSPLIT(TRIM(UPPER($B5))," ",,TRUE),1,1,TRUE)),puestos!$C$2:$C$324,puestos!$B$2:$B$324),"SIN PUESTO")) -> ANALISTA CONTABLE
A6: 10005 | B6: JOSE ANTONIO MARTINEZ MARTINEZ | C6: jmmartinez@cafepuntadelcielo.co | D6: MAMA690525TBA | E6: EDGAR ALVAREZ RIOS | F6: FINANZAS | G6: CONTABILIDAD | H6: ADMINISTRATIVO | I6: 36 | J6: 20/03/2013 | L6: =IF($B6="","",IFERROR(_xlfn.XLOOKUP(_xlfn.TEXTJOIN(" ",TRUE,_xlfn._xlws.SORT(_xlfn.TEXTSPLIT(TRIM(UPPER($B6))," ",,TRUE),1,1,TRUE)),puestos!$C$2:$C$324,puestos!$B$2:$B$324),"SIN PUESTO")) -> ANALISTA CONTABLE
A7: 10006 | B7: EDUARDO CAMACHO MEDINA | C7: emedina@cafepuntadelcielo.co | D7: CAME690120RT2 | E7: ABRAHAM ISAIAS PADRON CASTRO | F7: LOGISTICA & OPERACIONES | G7: LOGISTICA | H7: ADMINISTRATIVO | I7: 35 | J7: 09/04/2013 | L7: =IF($B7="","",IFERROR(_xlfn.XLOOKUP(_xlfn.TEXTJOIN(" ",TRUE,_xlfn._xlws.SORT(_xlfn.TEXTSPLIT(TRIM(UPPER($B7))," ",,TRUE),1,1,TRUE)),puestos!$C$2:$C$324,puestos!$B$2:$B$324),"SIN PUESTO")) -> ESPECIALISTA CONTABLE
A8: 10007 | B8: ADRIANA GARCIA PARRA | C8: agparra@cafepuntadelcielo.co | D8: GAPA7603051T9 | E8: JOAQUIN CURIEL SANCHEZ | F8: LOGISTICA & OPERACIONES | G8: SERVICIO AL CLIENTE | H8: ADMINISTRATIVO | I8: 48 | J8: 01/08/2013 | L8: =IF($B8="","",IFERROR(_xlfn.XLOOKUP(_xlfn.TEXTJOIN(" ",TRUE,_xlfn._xlws.SORT(_xlfn.TEXTSPLIT(TRIM(UPPER($B8))," ",,TRUE),1,1,TRUE)),puestos!$C$2:$C$324,puestos!$B$2:$B$324),"SIN PUESTO")) -> COORDINADOR SAC
A9: 10008 | B9: NEIDY MARTINEZ MARTINEZ | C9: neidym@cafepuntadelcielo.co | D9: MAMN771201UV0 | E9: ALBIN SAMUEL GOMEZ PINZON | F9: GENTE & GESTION | G9: GENTE Y GESTION | H9: ADMINISTRATIVO | I9: 50 | J9: 04/11/2013 | L9: =IF($B9="","",IFERROR(_xlfn.XLOOKUP(_xlfn.TEXTJOIN(" ",TRUE,_xlfn._xlws.SORT(_xlfn.TEXTSPLIT(TRIM(UPPER($B9))," ",,TRUE),1,1,TRUE)),puestos!$C$2:$C$324,puestos!$B$2:$B$324),"SIN PUESTO")) -> ANALISTA DE SERVICIOS GENERALES
A10: 10009 | B10: ANAYELI GARCIA MINGOLE | C10: amingole@cafepuntadelcielo.co | D10: GAMA880627D13 | E10: ALBIN SAMUEL GOMEZ PINZON | F10: GENTE & GESTION | G10: GENTE Y GESTIÓN PLANTA | H10: ADMINISTRATIVO | I10: 61 | J10: 14/07/2014 | K10: SI | L10: =IF($B10="","",IFERROR(_xlfn.XLOOKUP(_xlfn.TEXTJOIN(" ",TRUE,_xlfn._xlws.SORT(_xlfn.TEXTSPLIT(TRIM(UPPER($B10))," ",,TRUE),1,1,TRUE)),puestos!$C$2:$C$324,puestos!$B$2:$B$324),"SIN PUESTO")) -> JEFE DE G&G
A11: 10010 | B11: ALMA DELIA HERRERA VAZQUEZ | C11: advazquez@cafepuntadelcielo.co | D11: HEVA891006NJA | E11: ARMANDO RODRIGUEZ NAVARRETE | F11: MANUFACTURA | G11: ADMINISTRACION PLANTA | H11: ADMINISTRATIVO | I11: 42 | J11: 15/01/2015 | L11: =IF($B11="","",IFERROR(_xlfn.XLOOKUP(_xlfn.TEXTJOIN(" ",TRUE,_xlfn._xlws.SORT(_xlfn.TEXTSPLIT(TRIM(UPPER($B11))," ",,TRUE),1,1,TRUE)),puestos!$C$2:$C$324,puestos!$B$2:$B$324),"SIN PUESTO")) -> JEFE DE PRODUCCION
A12: 10011 | B12: CARMEN EDITH JIMENEZ DEL RAZO | C12: cjrazo@cafepuntadelcielo.co | D12: JIRC921129R29 | E12: HUGO CESAR GARCIA PEREZ | F12: LEGAL | G12: JURIDICO | H12: ADMINISTRATIVO | I12: 44 | J12: 20/12/2016 | L12: =IF($B12="","",IFERROR(_xlfn.XLOOKUP(_xlfn.TEXTJOIN(" ",TRUE,_xlfn._xlws.SORT(_xlfn.TEXTSPLIT(TRIM(UPPER($B12))," ",,TRUE),1,1,TRUE)),puestos!$C$2:$C$324,puestos!$B$2:$B$324),"SIN PUESTO")) -> JEFE DE SOSTENIBILIDAD
A13: 10012 | B13: CARLOS CALIXTRO HERNANDEZ | C13: ccalixtro@cafepuntadelcielo.co | D13: CAHC670821SS2 | E13: DIEGO ARMANDO SANCHEZ OJEDA | F13: LOGISTICA & OPERACIONES | G13: LOGISTICA | H13: ADMINISTRATIVO | I13: 34 | J13: 22/05/2017 | L13: =IF($B13="","",IFERROR(_xlfn.XLOOKUP(_xlfn.TEXTJOIN(" ",TRUE,_xlfn._xlws.SORT(_xlfn.TEXTSPLIT(TRIM(UPPER($B13))," ",,TRUE),1,1,TRUE)),puestos!$C$2:$C$324,puestos!$B$2:$B$324),"SIN PUESTO")) -> COORDINADOR DE BODEGA
A14: 10013 | B14: CINTHIA PAOLA NEGRETE CHAVEZ | D14: NECC841216H29 | E14: NEIDY MARTINEZ MARTINEZ | F14: LOGISTICA & OPERACIONES | G14: INTENDENCIA | H14: OPERATIVO | I14: 27 | J14: 14/11/2017 | L14: =IF($B14="","",IFERROR(_xlfn.XLOOKUP(_xlfn.TEXTJOIN(" ",TRUE,_xlfn._xlws.SORT(_xlfn.TEXTSPLIT(TRIM(UPPER($B14))," ",,TRUE),1,1,TRUE)),puestos!$C$2:$C$324,puestos!$B$2:$B$324),"SIN PUESTO")) -> AUXILIAR DE LIMPIEZA
A15: 10014 | B15: ALEJANDRO MEDINA ORTEGA | C15: amortega@cafepuntadelcielo.co | D15: MEOA881117FB0 | E15: JOAQUIN CURIEL SANCHEZ | F15: LOGISTICA & OPERACIONES | G15: SERVICIO AL CLIENTE | H15: ADMINISTRATIVO | I15: 44 | J15: 07/04/2018 | L15: =IF($B15="","",IFERROR(_xlfn.XLOOKUP(_xlfn.TEXTJOIN(" ",TRUE,_xlfn._xlws.SORT(_xlfn.TEXTSPLIT(TRIM(UPPER($B15))," ",,TRUE),1,1,TRUE)),puestos!$C$2:$C$324,puestos!$B$2:$B$324),"SIN PUESTO")) -> COORDINADOR SAC
A16: 10015 | B16: ESTEPHANY COLIN MAYEN | C16: ecolin@cafepuntadelcielo.co | D16: COME920924JI3 | E16: LUIS ALBERTO MONTIEL MANSO | F16: MARKETING | G16: MARKETING | H16: ADMINISTRATIVO | I16: 24 | J16: 17/04/2018 | L16: =IF($B16="","",IFERROR(_xlfn.XLOOKUP(_xlfn.TEXTJOIN(" ",TRUE,_xlfn._xlws.SORT(_xlfn.TEXTSPLIT(TRIM(UPPER($B16))," ",,TRUE),1,1,TRUE)),puestos!$C$2:$C$324,puestos!$B$2:$B$324),"SIN PUESTO")) -> ESPECIALISTA DE MARKETING
A17: 10016 | B17: JOSE GERARDO SERVIN FLORES | D17: SEFG751021NF7 | E17: LIZBETH RODRIGUEZ RODRIGUEZ | F17: LOGISTICA & OPERACIONES | G17: LOGISTICA | H17: OPERATIVO | I17: 30 | J17: 29/05/2018 | L17: =IF($B17="","",IFERROR(_xlfn.XLOOKUP(_xlfn.TEXTJOIN(" ",TRUE,_xlfn._xlws.SORT(_xlfn.TEXTSPLIT(TRIM(UPPER($B17))," ",,TRUE),1,1,TRUE)),puestos!$C$2:$C$324,puestos!$B$2:$B$324),"SIN PUESTO")) -> CHOFER
A18: 10017 | B18: JORGE ANTONIO JIMENEZ UGALDE | C18: jajimenez@cafepuntadelcielo.co | D18: JIUJ880317H43 | E18: CARLOS ARTURO RODRIGUEZ MARCIA | F18: COMERCIAL | G18: COMERCIAL | H18: ADMINISTRATIVO | I18: 38 | J18: 04/03/2019 | L18: =IF($B18="","",IFERROR(_xlfn.XLOOKUP(_xlfn.TEXTJOIN(" ",TRUE,_xlfn._xlws.SORT(_xlfn.TEXTSPLIT(TRIM(UPPER($B18))," ",,TRUE),1,1,TRUE)),puestos!$C$2:$C$324,puestos!$B$2:$B$324),"SIN PUESTO")) -> GERENTE COMERCIAL
A19: 10018 | B19: CARLOS MONREAL MORAN | D19: MOMC751111B56 | E19: DIEGO ARMANDO SANCHEZ OJEDA | F19: LOGISTICA & OPERACIONES | G19: LOGISTICA | H19: OPERATIVO | I19: 44 | J19: 20/05/2019 | L19: =IF($B19="","",IFERROR(_xlfn.XLOOKUP(_xlfn.TEXTJOIN(" ",TRUE,_xlfn._xlws.SORT(_xlfn.TEXTSPLIT(TRIM(UPPER($B19))," ",,TRUE),1,1,TRUE)),puestos!$C$2:$C$324,puestos!$B$2:$B$324),"SIN PUESTO")) -> AUXILIAR DE BODEGA
A20: 10019 | B20: ALMA RANGEL AYALA | C20: arangel@cafepuntadelcielo.co | D20: RAAA730514SL7 | E20: LIZBETH RODRIGUEZ RODRIGUEZ | F20: LOGISTICA & OPERACIONES | G20: LOGISTICA | H20: ADMINISTRATIVO | I20: 44 | J20: 03/06/2019 | L20: =IF($B20="","",IFERROR(_xlfn.XLOOKUP(_xlfn.TEXTJOIN(" ",TRUE,_xlfn._xlws.SORT(_xlfn.TEXTSPLIT(TRIM(UPPER($B20))," ",,TRUE),1,1,TRUE)),puestos!$C$2:$C$324,puestos!$B$2:$B$324),"SIN PUESTO")) -> COORDINADOR DE TRANSPORTE
A21: 10020 | B21: GUSTAVO FITZ BLAS | C21: gfitz@cafepuntadelcielo.co | D21: FIBG870522PB0 | E21: JOAQUIN CURIEL SANCHEZ | F21: LOGISTICA & OPERACIONES | G21: SERVICIO AL CLIENTE | H21: ADMINISTRATIVO | I21: 44 | J21: 17/06/2019 | L21: =IF($B21="","",IFERROR(_xlfn.XLOOKUP(_xlfn.TEXTJOIN(" ",TRUE,_xlfn._xlws.SORT(_xlfn.TEXTSPLIT(TRIM(UPPER($B21))," ",,TRUE),1,1,TRUE)),puestos!$C$2:$C$324,puestos!$B$2:$B$324),"SIN PUESTO")) -> COORDINADOR SAC
A22: 10021 | B22: OSCAR RAMON MENDOZA CAMACHO | D22: MECO8912101A7 | E22: LIZBETH RODRIGUEZ RODRIGUEZ | F22: LOGISTICA & OPERACIONES | G22: LOGISTICA | H22: OPERATIVO | I22: 44 | J22: 15/07/2019 | L22: =IF($B22="","",IFERROR(_xlfn.XLOOKUP(_xlfn.TEXTJOIN(" ",TRUE,_xlfn._xlws.SORT(_xlfn.TEXTSPLIT(TRIM(UPPER($B22))," ",,TRUE),1,1,TRUE)),puestos!$C$2:$C$324,puestos!$B$2:$B$324),"SIN PUESTO")) -> CHOFER
A23: 10022 | B23: MARCO ANTONIO RUIZ MORALES | D23: RUMM751230198 | E23: LIZBETH RODRIGUEZ RODRIGUEZ | F23: LOGISTICA & OPERACIONES | G23: LOGISTICA | H23: OPERATIVO | I23: 37 | J23: 12/08/2019 | L23: =IF($B23="","",IFERROR(_xlfn.XLOOKUP(_xlfn.TEXTJOIN(" ",TRUE,_xlfn._xlws.SORT(_xlfn.TEXTSPLIT(TRIM(UPPER($B23))," ",,TRUE),1,1,TRUE)),puestos!$C$2:$C$324,puestos!$B$2:$B$324),"SIN PUESTO")) -> CHOFER
A24: 10023 | B24: ANDRES PEREZ ABAD | C24: aabad@cafepuntadelcielo.co | D24: PEAA891012GJ2 | E24: EDGAR ALVAREZ RIOS | F24: FINANZAS | G24: CONTABILIDAD | H24: ADMINISTRATIVO | I24: 44 | J24: 19/08/2019 | L24: =IF($B24="","",IFERROR(_xlfn.XLOOKUP(_xlfn.TEXTJOIN(" ",TRUE,_xlfn._xlws.SORT(_xlfn.TEXTSPLIT(TRIM(UPPER($B24))," ",,TRUE),1,1,TRUE)),puestos!$C$2:$C$324,puestos!$B$2:$B$324),"SIN PUESTO")) -> ANALISTA CONTABLE
A25: 10024 | B25: DANIEL MACIAS PREZA | C25: dmacias@cafepuntadelcielo.co | D25: MAPD920915PN0 | E25: EDGAR ALVAREZ RIOS | F25: FINANZAS | G25: CONTABILIDAD | H25: ADMINISTRATIVO | I25: 33 | J25: 26/08/2019 | L25: =IF($B25="","",IFERROR(_xlfn.XLOOKUP(_xlfn.TEXTJOIN(" ",TRUE,_xlfn._xlws.SORT(_xlfn.TEXTSPLIT(TRIM(UPPER($B25))," ",,TRUE),1,1,TRUE)),puestos!$C$2:$C$324,puestos!$B$2:$B$324),"SIN PUESTO")) -> COORDINADOR CONTABLE
A26: 10025 | B26: DIEGO ARMANDO SANCHEZ OJEDA | C26: dasanchez@cafepuntadelcielo.co | D26: SAOD840706NI0 | E26: DAVID ARTURO DIAZ RAMIREZ | F26: LOGISTICA & OPERACIONES | G26: LOGISTICA | H26: ADMINISTRATIVO | I26: 37 | J26: 26/08/2019 | L26: =IF($B26="","",IFERROR(_xlfn.XLOOKUP(_xlfn.TEXTJOIN(" ",TRUE,_xlfn._xlws.SORT(_xlfn.TEXTSPLIT(TRIM(UPPER($B26))," ",,TRUE),1,1,TRUE)),puestos!$C$2:$C$324,puestos!$B$2:$B$324),"SIN PUESTO")) -> JEFE DE BODEGA
A27: 10026 | B27: JAZMIN VAZQUEZ CRUZ | C27: jvcruz@cafepuntadelcielo.co | D27: VACJ931002HA7 | E27: ANA LILIA MENDOZA TORRES | F27: FINANZAS | G27: CUENTAS POR COBRAR | H27: ADMINISTRATIVO | I27: 64 | J27: 26/11/2019 | L27: =IF($B27="","",IFERROR(_xlfn.XLOOKUP(_xlfn.TEXTJOIN(" ",TRUE,_xlfn._xlws.SORT(_xlfn.TEXTSPLIT(TRIM(UPPER($B27))," ",,TRUE),1,1,TRUE)),puestos!$C$2:$C$324,puestos!$B$2:$B$324),"SIN PUESTO")) -> ANALISTA CUENTAS POR PAGAR
A28: 10027 | B28: IVONNE BADILLO TORRES | C28: ibadillo@cafepuntadelcielo.co | D28: BATI930823UTA | E28: LUIS ANTONIO SANTOS HERNANDEZ | F28: GENTE & GESTION | G28: GENTE Y GESTION | H28: ADMINISTRATIVO | I28: 19 | J28: 04/02/2020 | L28: =IF($B28="","",IFERROR(_xlfn.XLOOKUP(_xlfn.TEXTJOIN(" ",TRUE,_xlfn._xlws.SORT(_xlfn.TEXTSPLIT(TRIM(UPPER($B28))," ",,TRUE),1,1,TRUE)),puestos!$C$2:$C$324,puestos!$B$2:$B$324),"SIN PUESTO")) -> COORDINADOR DE NOMINA
A29: 10028 | B29: VICTOR HUGO LOPEZ HERNANDEZ | D29: LOHV861204G12 | E29: DIEGO ARMANDO SANCHEZ OJEDA | F29: LOGISTICA & OPERACIONES | G29: LOGISTICA | H29: OPERATIVO | I29: 29 | J29: 24/02/2020 | L29: =IF($B29="","",IFERROR(_xlfn.XLOOKUP(_xlfn.TEXTJOIN(" ",TRUE,_xlfn._xlws.SORT(_xlfn.TEXTSPLIT(TRIM(UPPER($B29))," ",,TRUE),1,1,TRUE)),puestos!$C$2:$C$324,puestos!$B$2:$B$324),"SIN PUESTO")) -> AUXILIAR DE BODEGA
A30: 10029 | B30: LUIS FELIPE ROMAN NONOAL | C30: lroman@cafeportales.com | D30: RONL9303013C0 | E30: LUIS ANTONIO SANTOS HERNANDEZ | F30: GENTE & GESTION | G30: GENTE Y GESTION | H30: ADMINISTRATIVO | I30: 22 | J30: 06/04/2020 | L30: =IF($B30="","",IFERROR(_xlfn.XLOOKUP(_xlfn.TEXTJOIN(" ",TRUE,_xlfn._xlws.SORT(_xlfn.TEXTSPLIT(TRIM(UPPER($B30))," ",,TRUE),1,1,TRUE)),puestos!$C$2:$C$324,puestos!$B$2:$B$324),"SIN PUESTO")) -> COORDINADOR DE NOMINA
A31: 10030 | B31: ALEJANDRA BERENICE DAVID CAMACHO | C31: adavid@cafepuntadelcielo.co | D31: DACA900723S81 | E31: LUIS ALBERTO MONTIEL MANSO | F31: MARKETING | G31: MARKETING | H31: ADMINISTRATIVO | I31: 40 | J31: 06/11/2020 | L31: =IF($B31="","",IFERROR(_xlfn.XLOOKUP(_xlfn.TEXTJOIN(" ",TRUE,_xlfn._xlws.SORT(_xlfn.TEXTSPLIT(TRIM(UPPER($B31))," ",,TRUE),1,1,TRUE)),puestos!$C$2:$C$324,puestos!$B$2:$B$324),"SIN PUESTO")) -> ESPECIALISTA DE DISEÑO GRAFICO
A32: 10031 | B32: MAYRA SOFIA BARON ROJAS | C32: mbaron@cafepuntadelcielo.co | D32: BARM750918IF9 | E32: DIEGO ARMANDO SANCHEZ OJEDA | F32: LOGISTICA & OPERACIONES | G32: LOGISTICA | H32: ADMINISTRATIVO | I32: 42 | J32: 09/12/2020 | L32: =IF($B32="","",IFERROR(_xlfn.XLOOKUP(_xlfn.TEXTJOIN(" ",TRUE,_xlfn._xlws.SORT(_xlfn.TEXTSPLIT(TRIM(UPPER($B32))," ",,TRUE),1,1,TRUE)),puestos!$C$2:$C$324,puestos!$B$2:$B$324),"SIN PUESTO")) -> VERIFICADOR
A33: 10032 | B33: JOAQUIN RODRIGUEZ CORONA | D33: ROCJ7105068A0 | E33: LIZBETH RODRIGUEZ RODRIGUEZ | F33: LOGISTICA & OPERACIONES | G33: LOGISTICA | H33: OPERATIVO | I33: 14 | J33: 20/01/2021 | L33: =IF($B33="","",IFERROR(_xlfn.XLOOKUP(_xlfn.TEXTJOIN(" ",TRUE,_xlfn._xlws.SORT(_xlfn.TEXTSPLIT(TRIM(UPPER($B33))," ",,TRUE),1,1,TRUE)),puestos!$C$2:$C$324,puestos!$B$2:$B$324),"SIN PUESTO")) -> CHOFER
A34: 10033 | B34: FERNANDO REYES SANCHEZ | D34: RESF850802T65 | E34: LIZBETH RODRIGUEZ RODRIGUEZ | F34: LOGISTICA & OPERACIONES | G34: LOGISTICA | H34: OPERATIVO | I34: 36 | J34: 08/04/2021 | L34: =IF($B34="","",IFERROR(_xlfn.XLOOKUP(_xlfn.TEXTJOIN(" ",TRUE,_xlfn._xlws.SORT(_xlfn.TEXTSPLIT(TRIM(UPPER($B34))," ",,TRUE),1,1,TRUE)),puestos!$C$2:$C$324,puestos!$B$2:$B$324),"SIN PUESTO")) -> CHOFER
A35: 10034 | B35: MARCO ANTONIO CADENAS HERNANDEZ | D35: CAHM010308PZ0 | E35: DIEGO ARMANDO SANCHEZ OJEDA | F35: LOGISTICA & OPERACIONES | G35: LOGISTICA | H35: OPERATIVO | I35: 38 | J35: 24/05/2021 | L35: =IF($B35="","",IFERROR(_xlfn.XLOOKUP(_xlfn.TEXTJOIN(" ",TRUE,_xlfn._xlws.SORT(_xlfn.TEXTSPLIT(TRIM(UPPER($B35))," ",,TRUE),1,1,TRUE)),puestos!$C$2:$C$324,puestos!$B$2:$B$324),"SIN PUESTO")) -> AUXILIAR DE BODEGA
A36: 10035 | B36: NANCY ESCALONA MEXICA | C36: nescalona@cafepuntadelcielo.co | D36: EAMN790918SN0 | E36: FELIPE CORTES CAZAREZ | F36: COMERCIAL | G36: COMERCIAL | H36: ADMINISTRATIVO | I36: 34 | J36: 24/05/2021 | L36: =IF($B36="","",IFERROR(_xlfn.XLOOKUP(_xlfn.TEXTJOIN(" ",TRUE,_xlfn._xlws.SORT(_xlfn.TEXTSPLIT(TRIM(UPPER($B36))," ",,TRUE),1,1,TRUE)),puestos!$C$2:$C$324,puestos!$B$2:$B$324),"SIN PUESTO")) -> ESPECIALISTA DE OBZ COMERCIAL
A37: 10036 | B37: NATALIA SOFIA MARTINEZ HERNANDEZ | D37: MAHN740719D64 | E37: LIZBETH RODRIGUEZ RODRIGUEZ | F37: LOGISTICA & OPERACIONES | G37: MONITOREO | H37: OPERATIVO | I37: 38 | J37: 07/06/2021 | L37: =IF($B37="","",IFERROR(_xlfn.XLOOKUP(_xlfn.TEXTJOIN(" ",TRUE,_xlfn._xlws.SORT(_xlfn.TEXTSPLIT(TRIM(UPPER($B37))," ",,TRUE),1,1,TRUE)),puestos!$C$2:$C$324,puestos!$B$2:$B$324),"SIN PUESTO")) -> AUXILIAR DE MONITOREO
A38: 10037 | B38: DIEGO BARRIENTOS RIVERA | C38: dbarrientos@biabrands.co | D38: BARD970115K9A | E38: TANIA CHANTHAL JACINTO TORRES | F38: LEGAL | G38: JURIDICO | H38: ADMINISTRATIVO | I38: 31 | J38: 02/08/2021 | L38: =IF($B38="","",IFERROR(_xlfn.XLOOKUP(_xlfn.TEXTJOIN(" ",TRUE,_xlfn._xlws.SORT(_xlfn.TEXTSPLIT(TRIM(UPPER($B38))," ",,TRUE),1,1,TRUE)),puestos!$C$2:$C$324,puestos!$B$2:$B$324),"SIN PUESTO")) -> ESPECIALISTA JURIDICO
A39: 10038 | B39: CLAUDIA OLIVIA RODRIGUEZ LOPEZ | C39: corodriguez@cafepuntadelcielo.co | D39: ROLC631123SY2 | E39: BRENDA ROJAS MONROY | F39: FINANZAS | G39: CUENTAS POR PAGAR | H39: ADMINISTRATIVO | I39: 38 | J39: 30/08/2021 | L39: =IF($B39="","",IFERROR(_xlfn.XLOOKUP(_xlfn.TEXTJOIN(" ",TRUE,_xlfn._xlws.SORT(_xlfn.TEXTSPLIT(TRIM(UPPER($B39))," ",,TRUE),1,1,TRUE)),puestos!$C$2:$C$324,puestos!$B$2:$B$324),"SIN PUESTO")) -> ANALISTA CUENTAS POR PAGAR
A40: 10039 | B40: RODRIGO EMMANUEL CALIXTRO MORENO | D40: CAMR990929BJ0 | E40: DIEGO ARMANDO SANCHEZ OJEDA | F40: LOGISTICA & OPERACIONES | G40: LOGISTICA | H40: OPERATIVO | I40: 54 | J40: 26/11/2021 | L40: =IF($B40="","",IFERROR(_xlfn.XLOOKUP(_xlfn.TEXTJOIN(" ",TRUE,_xlfn._xlws.SORT(_xlfn.TEXTSPLIT(TRIM(UPPER($B40))," ",,TRUE),1,1,TRUE)),puestos!$C$2:$C$324,puestos!$B$2:$B$324),"SIN PUESTO")) -> AUXILIAR DE BODEGA
A41: 10040 | B41: MICHAEL KARINA CARRETERO LOPEZ | C41: mcarretero@cafepuntadelcielo.co | D41: CALM890730945 | E41: ALBIN SAMUEL GOMEZ PINZON | F41: GENTE & GESTION | G41: GENTE Y GESTION | H41: ADMINISTRATIVO | I41: 18 | J41: 10/01/2022 | K41: SI | L41: =IF($B41="","",IFERROR(_xlfn.XLOOKUP(_xlfn.TEXTJOIN(" ",TRUE,_xlfn._xlws.SORT(_xlfn.TEXTSPLIT(TRIM(UPPER($B41))," ",,TRUE),1,1,TRUE)),puestos!$C$2:$C$324,puestos!$B$2:$B$324),"SIN PUESTO")) -> COORDINADOR G&G
A42: 10041 | B42: BRENDA ROJAS MONROY | C42: brojas@cafepuntadelcielo.co | D42: ROMB810510H30 | E42: ANA MARIA DEL CARMEN VERTIZ ESTEVEZ | F42: FINANZAS | G42: CUENTAS POR PAGAR | H42: ADMINISTRATIVO | I42: 34 | J42: 24/01/2022 | L42: =IF($B42="","",IFERROR(_xlfn.XLOOKUP(_xlfn.TEXTJOIN(" ",TRUE,_xlfn._xlws.SORT(_xlfn.TEXTSPLIT(TRIM(UPPER($B42))," ",,TRUE),1,1,TRUE)),puestos!$C$2:$C$324,puestos!$B$2:$B$324),"SIN PUESTO")) -> JEFE DE CUENTAS POR PAGAR
A43: 10042 | B43: ERICK FABIAN CAÑAS GONZALEZ | C43: ecanas@cafepuntadelcielo.co | D43: CAGE860501QGA | E43: ANA MARIA DEL CARMEN VERTIZ ESTEVEZ | F43: FINANZAS | G43: SISTEMAS | H43: ADMINISTRATIVO | I43: 34 | J43: 07/03/2022 | L43: =IF($B43="","",IFERROR(_xlfn.XLOOKUP(_xlfn.TEXTJOIN(" ",TRUE,_xlfn._xlws.SORT(_xlfn.TEXTSPLIT(TRIM(UPPER($B43))," ",,TRUE),1,1,TRUE)),puestos!$C$2:$C$324,puestos!$B$2:$B$324),"SIN PUESTO")) -> ANALISTA IT
A44: 10043 | B44: AUGUSTO ALONSO GUTIERREZ VITE | C44: agvite@cafepuntadelcielo.co | D44: GUVA790416ME6 | E44: FELIPE CORTES CAZAREZ | F44: COMERCIAL | G44: VENTAS | H44: ADMINISTRATIVO | I44: 34 | J44: 18/04/2022 | L44: =IF($B44="","",IFERROR(_xlfn.XLOOKUP(_xlfn.TEXTJOIN(" ",TRUE,_xlfn._xlws.SORT(_xlfn.TEXTSPLIT(TRIM(UPPER($B44))," ",,TRUE),1,1,TRUE)),puestos!$C$2:$C$324,puestos!$B$2:$B$324),"SIN PUESTO")) -> COORDINADOR ADMINISTRATIVO TRADE
A45: 10044 | B45: GRECIA VEGA HERNANDEZ | C45: gvega@cafepuntadelcielo.co | D45: VEHG970303HN4 | E45: CARMEN EDITH JIMENEZ DEL RAZO | F45: LEGAL | G45: JURIDICO | H45: ADMINISTRATIVO | I45: 27 | J45: 02/05/2022 | L45: =IF($B45="","",IFERROR(_xlfn.XLOOKUP(_xlfn.TEXTJOIN(" ",TRUE,_xlfn._xlws.SORT(_xlfn.TEXTSPLIT(TRIM(UPPER($B45))," ",,TRUE),1,1,TRUE)),puestos!$C$2:$C$324,puestos!$B$2:$B$324),"SIN PUESTO")) -> ANALISTA DE SOSTENIBILIDAD
A46: 10045 | B46: CECILIA GOMEZ RANGEL | C46: crangel@cafepuntadelcielo.co | D46: GORC8702018U0 | E46: ERIKA GARCIA ROMAN | F46: COMPRAS | G46: COMPRAS | H46: ADMINISTRATIVO | I46: 26 | J46: 30/05/2022 | L46: =IF($B46="","",IFERROR(_xlfn.XLOOKUP(_xlfn.TEXTJOIN(" ",TRUE,_xlfn._xlws.SORT(_xlfn.TEXTSPLIT(TRIM(UPPER($B46))," ",,TRUE),1,1,TRUE)),puestos!$C$2:$C$324,puestos!$B$2:$B$324),"SIN PUESTO")) -> COORDINADOR DE COMPRAS
A47: 10048 | B47: ARIANA GUTIERREZ MORALES | C47: agutierrezm@cafeportales.com | D47: GUMA941016KY9 | E47: GERARDO EMMANUEL SUAREZ PONCE | F47: LOGISTICA & OPERACIONES | G47: PLANEACION | H47: ADMINISTRATIVO | I47: 38 | J47: 08/08/2022 | L47: =IF($B47="","",IFERROR(_xlfn.XLOOKUP(_xlfn.TEXTJOIN(" ",TRUE,_xlfn._xlws.SORT(_xlfn.TEXTSPLIT(TRIM(UPPER($B47))," ",,TRUE),1,1,TRUE)),puestos!$C$2:$C$324,puestos!$B$2:$B$324),"SIN PUESTO")) -> COORDINADOR DE PLANIFICACION DE ABASTECIMIENTO
A48: 10049 | B48: ELIZABETH LOPEZ PALLARES | C48: epallares@cafepuntadelcielo.co | D48: LOPE7707077NA | E48: JORGE ANTONIO JIMENEZ UGALDE | F48: COMERCIAL | G48: FOOD SERVICE | H48: ADMINISTRATIVO | I48: 21 | J48: 29/08/2022 | L48: =IF($B48="","",IFERROR(_xlfn.XLOOKUP(_xlfn.TEXTJOIN(" ",TRUE,_xlfn._xlws.SORT(_xlfn.TEXTSPLIT(TRIM(UPPER($B48))," ",,TRUE),1,1,TRUE)),puestos!$C$2:$C$324,puestos!$B$2:$B$324),"SIN PUESTO")) -> EJECUTIVO DE FOOD SERVICE
A49: 10050 | B49: BENJAMIN RODRIGUEZ RANGEL | D49: RORB001210KI8 | E49: DIEGO ARMANDO SANCHEZ OJEDA | F49: LOGISTICA & OPERACIONES | G49: LOGISTICA | H49: OPERATIVO | I49: 27 | J49: 08/12/2022 | L49: =IF($B49="","",IFERROR(_xlfn.XLOOKUP(_xlfn.TEXTJOIN(" ",TRUE,_xlfn._xlws.SORT(_xlfn.TEXTSPLIT(TRIM(UPPER($B49))," ",,TRUE),1,1,TRUE)),puestos!$C$2:$C$324,puestos!$B$2:$B$324),"SIN PUESTO")) -> AUXILIAR DE BODEGA
A50: 10051 | B50: ARTURO SILVA SANTIAGO | C50: asantiago@cafepuntadelcielo.co | D50: SISA821002LG0 | E50: JORGE ANTONIO JIMENEZ UGALDE | F50: COMERCIAL | G50: VENTAS | H50: ADMINISTRATIVO | I50: 19 | J50: 23/01/2023 | L50: =IF($B50="","",IFERROR(_xlfn.XLOOKUP(_xlfn.TEXTJOIN(" ",TRUE,_xlfn._xlws.SORT(_xlfn.TEXTSPLIT(TRIM(UPPER($B50))," ",,TRUE),1,1,TRUE)),puestos!$C$2:$C$324,puestos!$B$2:$B$324),"SIN PUESTO")) -> KAM MAYOREO Y DISTRIBUIDORES
A51: 10052 | B51: JESUS MICHELL GARCIA HERNANDEZ | D51: GAHJ840926K6A | E51: LIZBETH RODRIGUEZ RODRIGUEZ | F51: LOGISTICA & OPERACIONES | G51: MONITOREO | H51: OPERATIVO | I51: 16 | J51: 13/02/2023 | L51: =IF($B51="","",IFERROR(_xlfn.XLOOKUP(_xlfn.TEXTJOIN(" ",TRUE,_xlfn._xlws.SORT(_xlfn.TEXTSPLIT(TRIM(UPPER($B51))," ",,TRUE),1,1,TRUE)),puestos!$C$2:$C$324,puestos!$B$2:$B$324),"SIN PUESTO")) -> AUXILIAR DE MONITOREO
A52: 10054 | B52: FELIPE CORTES CAZAREZ | C52: fcazarez@cafepuntadelcielo.co | D52: COCF8507211F7 | E52: JORGE ANTONIO JIMENEZ UGALDE | F52: COMERCIAL | G52: VENTAS | H52: ADMINISTRATIVO | I52: 11 | J52: 13/03/2023 | L52: =IF($B52="","",IFERROR(_xlfn.XLOOKUP(_xlfn.TEXTJOIN(" ",TRUE,_xlfn._xlws.SORT(_xlfn.TEXTSPLIT(TRIM(UPPER($B52))," ",,TRUE),1,1,TRUE)),puestos!$C$2:$C$324,puestos!$B$2:$B$324),"SIN PUESTO")) -> GERENTE TRADE MARKETING
A53: 10055 | B53: JONATHAN DAVID HERNANDEZ NEGRETE | D53: HENJ030614280 | E53: DIEGO ARMANDO SANCHEZ OJEDA | F53: LOGISTICA & OPERACIONES | G53: LOGISTICA | H53: OPERATIVO | I53: 25 | J53: 05/04/2023 | L53: =IF($B53="","",IFERROR(_xlfn.XLOOKUP(_xlfn.TEXTJOIN(" ",TRUE,_xlfn._xlws.SORT(_xlfn.TEXTSPLIT(TRIM(UPPER($B53))," ",,TRUE),1,1,TRUE)),puestos!$C$2:$C$324,puestos!$B$2:$B$324),"SIN PUESTO")) -> AUXILIAR DE BODEGA
A54: 10056 | B54: CHRISTIAN MONROY ZAMBRANO | D54: MOZC0111174F1 | E54: DIEGO ARMANDO SANCHEZ OJEDA | F54: LOGISTICA & OPERACIONES | G54: LOGISTICA | H54: OPERATIVO | I54: 18 | J54: 26/04/2023 | L54: =IF($B54="","",IFERROR(_xlfn.XLOOKUP(_xlfn.TEXTJOIN(" ",TRUE,_xlfn._xlws.SORT(_xlfn.TEXTSPLIT(TRIM(UPPER($B54))," ",,TRUE),1,1,TRUE)),puestos!$C$2:$C$324,puestos!$B$2:$B$324),"SIN PUESTO")) -> AUXILIAR DE BODEGA
A55: 10057 | B55: ENRIQUE BENITEZ GUERRERO | D55: BEGE790610KZ0 | E55: ELIZABETH LOPEZ PALLARES | F55: COMERCIAL | G55: FOOD SERVICE | H55: OPERATIVO | I55: 25 | J55: 04/07/2023 | L55: =IF($B55="","",IFERROR(_xlfn.XLOOKUP(_xlfn.TEXTJOIN(" ",TRUE,_xlfn._xlws.SORT(_xlfn.TEXTSPLIT(TRIM(UPPER($B55))," ",,TRUE),1,1,TRUE)),puestos!$C$2:$C$324,puestos!$B$2:$B$324),"SIN PUESTO")) -> TECNICO FOOD SERVICE
A56: 10058 | B56: GABRIEL RAMIREZ AMADOR | C56: gamador@cafepuntadelcielo.co | D56: RAAG910205QP4 | E56: ERIKA GARCIA ROMAN | F56: COMPRAS | G56: COMPRAS | H56: ADMINISTRATIVO | I56: 22 | J56: 15/08/2023 | L56: =IF($B56="","",IFERROR(_xlfn.XLOOKUP(_xlfn.TEXTJOIN(" ",TRUE,_xlfn._xlws.SORT(_xlfn.TEXTSPLIT(TRIM(UPPER($B56))," ",,TRUE),1,1,TRUE)),puestos!$C$2:$C$324,puestos!$B$2:$B$324),"SIN PUESTO")) -> COORDINADOR DE COMPRAS
A57: 10060 | B57: LILIANA MUÑOZ VAZQUEZ | C57: lvazquez@cafepuntadelcielo.co | D57: MUVL970901AZ1 | E57: DAVID ARTURO DIAZ RAMIREZ | F57: LOGISTICA & OPERACIONES | G57: LOGISTICA | H57: ADMINISTRATIVO | I57: 18 | J57: 15/01/2024 | L57: =IF($B57="","",IFERROR(_xlfn.XLOOKUP(_xlfn.TEXTJOIN(" ",TRUE,_xlfn._xlws.SORT(_xlfn.TEXTSPLIT(TRIM(UPPER($B57))," ",,TRUE),1,1,TRUE)),puestos!$C$2:$C$324,puestos!$B$2:$B$324),"SIN PUESTO")) -> CIT LOGISTICA
A58: 10061 | B58: CARLOS ADOLFO CRUZ MARTINEZ | D58: CUMC0310117W6 | E58: DIEGO ARMANDO SANCHEZ OJEDA | F58: LOGISTICA & OPERACIONES | G58: LOGISTICA | H58: OPERATIVO | I58: 14 | J58: 19/03/2024 | L58: =IF($B58="","",IFERROR(_xlfn.XLOOKUP(_xlfn.TEXTJOIN(" ",TRUE,_xlfn._xlws.SORT(_xlfn.TEXTSPLIT(TRIM(UPPER($B58))," ",,TRUE),1,1,TRUE)),puestos!$C$2:$C$324,puestos!$B$2:$B$324),"SIN PUESTO")) -> AUXILIAR DE BODEGA
A59: 10063 | B59: DAVID ARTURO DIAZ RAMIREZ | C59: aramirez@cafepuntadelcielo.co | D59: DIRD921006RJ5 | E59: ABRAHAM ISAIAS PADRON CASTRO | F59: LOGISTICA & OPERACIONES | G59: PLANEACION | H59: ADMINISTRATIVO | I59: 18 | J59: 01/04/2024 | L59: =IF($B59="","",IFERROR(_xlfn.XLOOKUP(_xlfn.TEXTJOIN(" ",TRUE,_xlfn._xlws.SORT(_xlfn.TEXTSPLIT(TRIM(UPPER($B59))," ",,TRUE),1,1,TRUE)),puestos!$C$2:$C$324,puestos!$B$2:$B$324),"SIN PUESTO")) -> GERENTE PLANEACION DE SUMINISTROS
A60: 10065 | B60: MAURICIO AUSTRIA LOPEZ | D60: AULM030802443 | E60: LIZBETH RODRIGUEZ RODRIGUEZ | F60: LOGISTICA & OPERACIONES | G60: MONITOREO | H60: OPERATIVO | I60: 26 | J60: 19/04/2024 | L60: =IF($B60="","",IFERROR(_xlfn.XLOOKUP(_xlfn.TEXTJOIN(" ",TRUE,_xlfn._xlws.SORT(_xlfn.TEXTSPLIT(TRIM(UPPER($B60))," ",,TRUE),1,1,TRUE)),puestos!$C$2:$C$324,puestos!$B$2:$B$324),"SIN PUESTO")) -> AUXILIAR DE MONITOREO
A61: 10066 | B61: GERARDO EMMANUEL SUAREZ PONCE | C61: gsuarez@cafepuntadelcielo.co | D61: SUPG900306RR5 | E61: ABRAHAM ISAIAS PADRON CASTRO | F61: LOGISTICA & OPERACIONES | G61: PLANEACION | H61: ADMINISTRATIVO | I61: 24 | J61: 29/04/2024 | L61: =IF($B61="","",IFERROR(_xlfn.XLOOKUP(_xlfn.TEXTJOIN(" ",TRUE,_xlfn._xlws.SORT(_xlfn.TEXTSPLIT(TRIM(UPPER($B61))," ",,TRUE),1,1,TRUE)),puestos!$C$2:$C$324,puestos!$B$2:$B$324),"SIN PUESTO")) -> GERENTE DE PLANIFICACION LOGISTICA
A62: 10067 | B62: CRISTINA MAGALI CASTRO MONTOYA | D62: CAMC850613272 | E62: NEIDY MARTINEZ MARTINEZ | F62: LOGISTICA & OPERACIONES | G62: INTENDENCIA | H62: OPERATIVO | I62: 13 | J62: 29/04/2024 | L62: =IF($B62="","",IFERROR(_xlfn.XLOOKUP(_xlfn.TEXTJOIN(" ",TRUE,_xlfn._xlws.SORT(_xlfn.TEXTSPLIT(TRIM(UPPER($B62))," ",,TRUE),1,1,TRUE)),puestos!$C$2:$C$324,puestos!$B$2:$B$324),"SIN PUESTO")) -> AUXILIAR DE LIMPIEZA
A63: 10068 | B63: ERIKA GARCIA ROMAN | C63: erikag@cafepuntadelcielo.co | D63: GARE731217SS7 | E63: ABRAHAM ISAIAS PADRON CASTRO | F63: COMPRAS | G63: COMPRAS | H63: ADMINISTRATIVO | I63: 26 | J63: 02/05/2024 | L63: =IF($B63="","",IFERROR(_xlfn.XLOOKUP(_xlfn.TEXTJOIN(" ",TRUE,_xlfn._xlws.SORT(_xlfn.TEXTSPLIT(TRIM(UPPER($B63))," ",,TRUE),1,1,TRUE)),puestos!$C$2:$C$324,puestos!$B$2:$B$324),"SIN PUESTO")) -> GERENTE DE COMPRAS
A64: 10069 | B64: SARA MONSERRAT JULIA ZALDIVAR CANOVAS | C64: szaldivar@cafepuntadelcielo.co | D64: ZACS920704P19 | E64: ALBIN SAMUEL GOMEZ PINZON | F64: GENTE & GESTION | G64: GENTE Y GESTION | H64: ADMINISTRATIVO | I64: 21 | J64: 06/05/2024 | K64: SI | L64: =IF($B64="","",IFERROR(_xlfn.XLOOKUP(_xlfn.TEXTJOIN(" ",TRUE,_xlfn._xlws.SORT(_xlfn.TEXTSPLIT(TRIM(UPPER($B64))," ",,TRUE),1,1,TRUE)),puestos!$C$2:$C$324,puestos!$B$2:$B$324),"SIN PUESTO")) -> COORDINADOR G&G
A65: 10070 | B65: ALFREDO EDUARDO MEJIA RODRIGUEZ | C65: amejia@cafepuntadelcielo.co | D65: MERA971116E65 | E65: GERARDO EMMANUEL SUAREZ PONCE | F65: LOGISTICA & OPERACIONES | G65: PLANEACION | H65: ADMINISTRATIVO | I65: 14 | J65: 03/06/2024 | L65: =IF($B65="","",IFERROR(_xlfn.XLOOKUP(_xlfn.TEXTJOIN(" ",TRUE,_xlfn._xlws.SORT(_xlfn.TEXTSPLIT(TRIM(UPPER($B65))," ",,TRUE),1,1,TRUE)),puestos!$C$2:$C$324,puestos!$B$2:$B$324),"SIN PUESTO")) -> COORDINADOR DE PLANIFICACION DE LA DEMANDA
A66: 10072 | B66: NIDIA CASTAÑEDA GALVAN | D66: CAGN67110697A | E66: NEIDY MARTINEZ MARTINEZ | F66: LOGISTICA & OPERACIONES | G66: INTENDENCIA | H66: OPERATIVO | I66: 19 | J66: 22/07/2024 | L66: =IF($B66="","",IFERROR(_xlfn.XLOOKUP(_xlfn.TEXTJOIN(" ",TRUE,_xlfn._xlws.SORT(_xlfn.TEXTSPLIT(TRIM(UPPER($B66))," ",,TRUE),1,1,TRUE)),puestos!$C$2:$C$324,puestos!$B$2:$B$324),"SIN PUESTO")) -> AUXILIAR DE LIMPIEZA
A67: 10073 | B67: AGUSTIN HERNANDEZ NAPOLES | C67: anapoles@cafepuntadelcielo.co | D67: HENA900116G58 | E67: LAURA ELENA DE LA ROSA SOTO | F67: FINANZAS | G67: IMPUESTOS | H67: ADMINISTRATIVO | I67: 26 | J67: 19/08/2024 | L67: =IF($B67="","",IFERROR(_xlfn.XLOOKUP(_xlfn.TEXTJOIN(" ",TRUE,_xlfn._xlws.SORT(_xlfn.TEXTSPLIT(TRIM(UPPER($B67))," ",,TRUE),1,1,TRUE)),puestos!$C$2:$C$324,puestos!$B$2:$B$324),"SIN PUESTO")) -> JEFE DE IMPUESTOS
A68: 10074 | B68: JHOVANY VALLEJAN SOLIS | C68: jvallejan@cafepuntadelcielo.co | D68: VASJ031209DG4 | E68: JOSE ANTONIO MARTINEZ MARTINEZ | F68: FINANZAS | G68: CONTABILIDAD | H68: ADMINISTRATIVO | I68: 26 | J68: 14/10/2024 | L68: =IF($B68="","",IFERROR(_xlfn.XLOOKUP(_xlfn.TEXTJOIN(" ",TRUE,_xlfn._xlws.SORT(_xlfn.TEXTSPLIT(TRIM(UPPER($B68))," ",,TRUE),1,1,TRUE)),puestos!$C$2:$C$324,puestos!$B$2:$B$324),"SIN PUESTO")) -> BECARIO
A69: 10075 | B69: DAFNE YUNNUEN TINOCO HERNANDEZ | C69: dtinoco@cafepuntadelcielo.co | D69: TIHD030226FA9 | E69: DANIEL MACIAS PREZA | F69: FINANZAS | G69: CONTABILIDAD | H69: ADMINISTRATIVO | I69: 24 | J69: 14/10/2024 | L69: =IF($B69="","",IFERROR(_xlfn.XLOOKUP(_xlfn.TEXTJOIN(" ",TRUE,_xlfn._xlws.SORT(_xlfn.TEXTSPLIT(TRIM(UPPER($B69))," ",,TRUE),1,1,TRUE)),puestos!$C$2:$C$324,puestos!$B$2:$B$324),"SIN PUESTO")) -> BECARIO
A70: 10076 | B70: ANGEL TERAN FRIAS | C70: ateran@cafeportales.com | D70: TEFA880901DM0 | E70: BRENDA ROJAS MONROY | F70: FINANZAS | G70: CUENTAS POR PAGAR | H70: ADMINISTRATIVO | I70: 26 | J70: 28/10/2024 | L70: =IF($B70="","",IFERROR(_xlfn.XLOOKUP(_xlfn.TEXTJOIN(" ",TRUE,_xlfn._xlws.SORT(_xlfn.TEXTSPLIT(TRIM(UPPER($B70))," ",,TRUE),1,1,TRUE)),puestos!$C$2:$C$324,puestos!$B$2:$B$324),"SIN PUESTO")) -> ANALISTA CUENTAS POR PAGAR
A71: 10078 | B71: LUIS EUGENIO GALLEGO SOTO | C71: lgallego@cafepuntadelcielo.co | D71: GASL6706234F0 | E71: JORGE ANTONIO JIMENEZ UGALDE | F71: COMERCIAL | G71: FOOD SERVICE | H71: ADMINISTRATIVO | I71: 26 | J71: 25/11/2024 | L71: =IF($B71="","",IFERROR(_xlfn.XLOOKUP(_xlfn.TEXTJOIN(" ",TRUE,_xlfn._xlws.SORT(_xlfn.TEXTSPLIT(TRIM(UPPER($B71))," ",,TRUE),1,1,TRUE)),puestos!$C$2:$C$324,puestos!$B$2:$B$324),"SIN PUESTO")) -> LEADER MAYOREOFOOD SERVICE
A72: 10080 | B72: EDUARDO GONZALEZ BARCENAS | C72: ebarcenas@cafepuntadelcielo.co | D72: GOBE8406164Y3 | E72: JOAQUIN CURIEL SANCHEZ | F72: LOGISTICA & OPERACIONES | G72: SERVICIO AL CLIENTE | H72: ADMINISTRATIVO | I72: 12 | J72: 17/02/2025 | L72: =IF($B72="","",IFERROR(_xlfn.XLOOKUP(_xlfn.TEXTJOIN(" ",TRUE,_xlfn._xlws.SORT(_xlfn.TEXTSPLIT(TRIM(UPPER($B72))," ",,TRUE),1,1,TRUE)),puestos!$C$2:$C$324,puestos!$B$2:$B$324),"SIN PUESTO")) -> FACTURADOR
A73: 10081 | B73: DIEGO ARMANDO AVILES ESTRELLA | C73: daviles@cafepuntadelcielo.co | D73: AIED870527BS7 | E73: JOAQUIN CURIEL SANCHEZ | F73: LOGISTICA & OPERACIONES | G73: SERVICIO AL CLIENTE | H73: ADMINISTRATIVO | I73: 7 | J73: 17/02/2025 | L73: =IF($B73="","",IFERROR(_xlfn.XLOOKUP(_xlfn.TEXTJOIN(" ",TRUE,_xlfn._xlws.SORT(_xlfn.TEXTSPLIT(TRIM(UPPER($B73))," ",,TRUE),1,1,TRUE)),puestos!$C$2:$C$324,puestos!$B$2:$B$324),"SIN PUESTO")) -> FACTURADOR
A74: 10082 | B74: ARMANDO RODRIGUEZ NAVARRETE | C74: anavarrete@cafepuntadelcielo.co | D74: RONA691128BY8 | E74: ABRAHAM ISAIAS PADRON CASTRO | F74: MANUFACTURA | G74: ADMINISTRACION PLANTA | H74: ADMINISTRATIVO | I74: 26 | J74: 10/03/2025 | L74: =IF($B74="","",IFERROR(_xlfn.XLOOKUP(_xlfn.TEXTJOIN(" ",TRUE,_xlfn._xlws.SORT(_xlfn.TEXTSPLIT(TRIM(UPPER($B74))," ",,TRUE),1,1,TRUE)),puestos!$C$2:$C$324,puestos!$B$2:$B$324),"SIN PUESTO")) -> GERENTE DE MANUFACTURA
A75: 10083 | B75: LAURA ELENA DE LA ROSA SOTO | C75: ldelarosa@cafepuntadelcielo.co | D75: ROSL750624B30 | E75: ANA MARIA DEL CARMEN VERTIZ ESTEVEZ | F75: FINANZAS | G75: FINANZAS | H75: ADMINISTRATIVO | I75: 12 | J75: 11/03/2025 | L75: =IF($B75="","",IFERROR(_xlfn.XLOOKUP(_xlfn.TEXTJOIN(" ",TRUE,_xlfn._xlws.SORT(_xlfn.TEXTSPLIT(TRIM(UPPER($B75))," ",,TRUE),1,1,TRUE)),puestos!$C$2:$C$324,puestos!$B$2:$B$324),"SIN PUESTO")) -> CONTROLLER FINANCIERO
A76: 10084 | B76: RUTH ESMERALDA FERNANDEZ VERGARA | C76: rfernandez@cafepuntadelcielo.co | D76: FEVR930627GY6 | E76: ABRAHAM ISAIAS PADRON CASTRO | F76: LOGISTICA & OPERACIONES | G76: LOGISTICA | H76: ADMINISTRATIVO | I76: 12 | J76: 18/03/2025 | L76: =IF($B76="","",IFERROR(_xlfn.XLOOKUP(_xlfn.TEXTJOIN(" ",TRUE,_xlfn._xlws.SORT(_xlfn.TEXTSPLIT(TRIM(UPPER($B76))," ",,TRUE),1,1,TRUE)),puestos!$C$2:$C$324,puestos!$B$2:$B$324),"SIN PUESTO")) -> JEFE DE EXPORTACIONES
A77: 10085 | B77: ANA MARIA DEL CARMEN VERTIZ ESTEVEZ | C77: avertiz@cafepuntadelcielo.co | D77: VEEA780713P92 | E77: CARLOS ARTURO RODRIGUEZ MARCIA | F77: FINANZAS | G77: FINANZAS | H77: ADMINISTRATIVO | I77: 12 | J77: 20/03/2025 | L77: =IF($B77="","",IFERROR(_xlfn.XLOOKUP(_xlfn.TEXTJOIN(" ",TRUE,_xlfn._xlws.SORT(_xlfn.TEXTSPLIT(TRIM(UPPER($B77))," ",,TRUE),1,1,TRUE)),puestos!$C$2:$C$324,puestos!$B$2:$B$324),"SIN PUESTO")) -> GERENTE FINANCIERO
A78: 10086 | B78: JORGE RIVERA AYALA | C78: jayala@cafepuntadelcielo.co | D78: RIAJ800128419 | E78: JOAQUIN CURIEL SANCHEZ | F78: LOGISTICA & OPERACIONES | G78: SERVICIO AL CLIENTE | H78: ADMINISTRATIVO | I78: 12 | J78: 31/03/2025 | L78: =IF($B78="","",IFERROR(_xlfn.XLOOKUP(_xlfn.TEXTJOIN(" ",TRUE,_xlfn._xlws.SORT(_xlfn.TEXTSPLIT(TRIM(UPPER($B78))," ",,TRUE),1,1,TRUE)),puestos!$C$2:$C$324,puestos!$B$2:$B$324),"SIN PUESTO")) -> FACTURADOR
A79: 10087 | B79: JUANA AIDE LOPEZ GARCIA | D79: LOGJ780528421 | E79: NEIDY MARTINEZ MARTINEZ | F79: LOGISTICA & OPERACIONES | G79: INTENDENCIA | H79: OPERATIVO | I79: 12 | J79: 16/05/2025 | L79: =IF($B79="","",IFERROR(_xlfn.XLOOKUP(_xlfn.TEXTJOIN(" ",TRUE,_xlfn._xlws.SORT(_xlfn.TEXTSPLIT(TRIM(UPPER($B79))," ",,TRUE),1,1,TRUE)),puestos!$C$2:$C$324,puestos!$B$2:$B$324),"SIN PUESTO")) -> AUXILIAR DE LIMPIEZA
A80: 10090 | B80: JUAN FERNANDO HERNANDEZ LOPEZ | D80: HELJ9603262E9 | E80: NEIDY MARTINEZ MARTINEZ | F80: LOGISTICA & OPERACIONES | G80: INTENDENCIA | H80: OPERATIVO | I80: 12 | J80: 16/06/2025 | L80: =IF($B80="","",IFERROR(_xlfn.XLOOKUP(_xlfn.TEXTJOIN(" ",TRUE,_xlfn._xlws.SORT(_xlfn.TEXTSPLIT(TRIM(UPPER($B80))," ",,TRUE),1,1,TRUE)),puestos!$C$2:$C$324,puestos!$B$2:$B$324),"SIN PUESTO")) -> AUXILIAR DE LIMPIEZA
A81: 10091 | B81: LUIS ALBERTO MONTIEL MANSO | C81: lmontiel@cafepuntadelcielo.co | D81: MOML8909266Q0 | E81: CARLOS ARTURO RODRIGUEZ MARCIA | F81: MARKETING | G81: MARKETING | H81: ADMINISTRATIVO | I81: 12 | J81: 23/07/2025 | L81: =IF($B81="","",IFERROR(_xlfn.XLOOKUP(_xlfn.TEXTJOIN(" ",TRUE,_xlfn._xlws.SORT(_xlfn.TEXTSPLIT(TRIM(UPPER($B81))," ",,TRUE),1,1,TRUE)),puestos!$C$2:$C$324,puestos!$B$2:$B$324),"SIN PUESTO")) -> GERENTE DE MARKETING
A82: 10092 | B82: JESUS DAVID PEREZ GARCIA | C82: jesusp@cafepuntadelcielo.co | D82: PEGJ771217MC0 | E82: JOAQUIN CURIEL SANCHEZ | F82: LOGISTICA & OPERACIONES | G82: SERVICIO AL CLIENTE | H82: ADMINISTRATIVO | I82: 12 | J82: 19/08/2025 | L82: =IF($B82="","",IFERROR(_xlfn.XLOOKUP(_xlfn.TEXTJOIN(" ",TRUE,_xlfn._xlws.SORT(_xlfn.TEXTSPLIT(TRIM(UPPER($B82))," ",,TRUE),1,1,TRUE)),puestos!$C$2:$C$324,puestos!$B$2:$B$324),"SIN PUESTO")) -> COORDINADOR DE FACTURACION
A83: 10093 | B83: MARIANA MINUET HERNANDEZ PINEDA | C83: marianap@cafepuntadelcielo.co | D83: HEPM9802198D1 | E83: AGUSTIN HERNANDEZ NAPOLES | F83: FINANZAS | G83: IMPUESTOS | H83: ADMINISTRATIVO | I83: 12 | J83: 25/08/2025 | L83: =IF($B83="","",IFERROR(_xlfn.XLOOKUP(_xlfn.TEXTJOIN(" ",TRUE,_xlfn._xlws.SORT(_xlfn.TEXTSPLIT(TRIM(UPPER($B83))," ",,TRUE),1,1,TRUE)),puestos!$C$2:$C$324,puestos!$B$2:$B$324),"SIN PUESTO")) -> ANALISTA FISCAL
A84: 10095 | B84: CARLOS ALBERTO MARTINEZ ZAVALETA | D84: MAZC950501G24 | E84: LIZBETH RODRIGUEZ RODRIGUEZ | F84: LOGISTICA & OPERACIONES | G84: LOGISTICA | H84: OPERATIVO | I84: 12 | J84: 06/10/2025 | L84: =IF($B84="","",IFERROR(_xlfn.XLOOKUP(_xlfn.TEXTJOIN(" ",TRUE,_xlfn._xlws.SORT(_xlfn.TEXTSPLIT(TRIM(UPPER($B84))," ",,TRUE),1,1,TRUE)),puestos!$C$2:$C$324,puestos!$B$2:$B$324),"SIN PUESTO")) -> CHOFER
A85: 10096 | B85: FERNANDA BETZABE MENDEZ RODRIGUEZ | C85: frodriguez@cafepuntadelcielo.co | D85: MERF000111245 | E85: ESAU RAMIREZ CABALLERO | F85: LEGAL | G85: JURIDICO | H85: ADMINISTRATIVO | I85: 12 | J85: 20/10/2025 | L85: =IF($B85="","",IFERROR(_xlfn.XLOOKUP(_xlfn.TEXTJOIN(" ",TRUE,_xlfn._xlws.SORT(_xlfn.TEXTSPLIT(TRIM(UPPER($B85))," ",,TRUE),1,1,TRUE)),puestos!$C$2:$C$324,puestos!$B$2:$B$324),"SIN PUESTO")) -> ESPECIALISTA JURIDICO
A86: 10097 | B86: CARLOS ARTURO RODRIGUEZ MARCIA | C86: carodriguez@biabrands.co | D86: ROMC8901063CA | E86: CARLOS ARTURO RODRIGUEZ MARCIA | F86: DIRECCION | G86: DIRECCIÓN GENERAL | H86: ADMINISTRATIVO | I86: 12 | J86: 01/02/2026 | L86: =IF($B86="","",IFERROR(_xlfn.XLOOKUP(_xlfn.TEXTJOIN(" ",TRUE,_xlfn._xlws.SORT(_xlfn.TEXTSPLIT(TRIM(UPPER($B86))," ",,TRUE),1,1,TRUE)),puestos!$C$2:$C$324,puestos!$B$2:$B$324),"SIN PUESTO")) -> GERENTE GENERAL
A87: 10098 | B87: CLAUDIA ELIZABETH PALMIERI CASIANO | C87: cpalmieri@cafepuntadelcielo.co | D87: PACC891102 | E87: EDGAR ALVAREZ RIOS | F87: FINANZAS | G87: CONTABILIDAD | H87: ADMINISTRATIVO | I87: 5 | J87: 24/02/2026 | L87: =IF($B87="","",IFERROR(_xlfn.XLOOKUP(_xlfn.TEXTJOIN(" ",TRUE,_xlfn._xlws.SORT(_xlfn.TEXTSPLIT(TRIM(UPPER($B87))," ",,TRUE),1,1,TRUE)),puestos!$C$2:$C$324,puestos!$B$2:$B$324),"SIN PUESTO")) -> COORDINADOR CONTABLE
A88: 10100 | B88: ISRAEL PALACIOS MENDEZ | C88: ipalacios@cafepuntadelcielo.co | D88: PAMI681217J39 | E88: ANA MARIA DEL CARMEN VERTIZ ESTEVEZ | F88: FINANZAS | G88: SISTEMAS | H88: ADMINISTRATIVO | I88: 22 | J88: 18/02/2019 | L88: =IF($B88="","",IFERROR(_xlfn.XLOOKUP(_xlfn.TEXTJOIN(" ",TRUE,_xlfn._xlws.SORT(_xlfn.TEXTSPLIT(TRIM(UPPER($B88))," ",,TRUE),1,1,TRUE)),puestos!$C$2:$C$324,puestos!$B$2:$B$324),"SIN PUESTO")) -> PROGRAMADOR SR
A89: 10101 | B89: DULCE ANGELICA SANCHEZ MARTINEZ | C89: dulces@cafepuntadelcielo.co | D89: SAMD981116Q74 | E89: ALBIN SAMUEL GOMEZ PINZON | F89: GENTE & GESTION | G89: GENTE Y GESTION | H89: ADMINISTRATIVO | I89: 38 | J89: 22/04/2021 | K89: SI | L89: =IF($B89="","",IFERROR(_xlfn.XLOOKUP(_xlfn.TEXTJOIN(" ",TRUE,_xlfn._xlws.SORT(_xlfn.TEXTSPLIT(TRIM(UPPER($B89))," ",,TRUE),1,1,TRUE)),puestos!$C$2:$C$324,puestos!$B$2:$B$324),"SIN PUESTO")) -> COORDINADOR DE DESARROLLO & GESTIÓN
A90: 10102 | B90: DAVID REYES HERNANDEZ | C90: davidh@cafepuntadelcielo.co | D90: REHD920809S13 | E90: ANA LILIA MENDOZA TORRES | F90: FINANZAS | G90: CUENTAS POR COBRAR | H90: ADMINISTRATIVO | I90: 40 | J90: 46139 | L90: =IF($B90="","",IFERROR(_xlfn.XLOOKUP(_xlfn.TEXTJOIN(" ",TRUE,_xlfn._xlws.SORT(_xlfn.TEXTSPLIT(TRIM(UPPER($B90))," ",,TRUE),1,1,TRUE)),puestos!$C$2:$C$324,puestos!$B$2:$B$324),"SIN PUESTO")) -> ANALISTA DE CUENTAS POR COBRAR
A91: 10104 | B91: OSCAR ALEJANDRO MALDONADO PEREZ | C91: oscarm@cafepuntadelcielo.co | D91: MAPO010811KP3 | E91: AGUSTIN HERNANDEZ NAPOLES | F91: FINANZAS | G91: IMPUESTOS | H91: ADMINISTRATIVO | I91: 31 | J91: 46331 | L91: =IF($B91="","",IFERROR(_xlfn.XLOOKUP(_xlfn.TEXTJOIN(" ",TRUE,_xlfn._xlws.SORT(_xlfn.TEXTSPLIT(TRIM(UPPER($B91))," ",,TRUE),1,1,TRUE)),puestos!$C$2:$C$324,puestos!$B$2:$B$324),"SIN PUESTO")) -> ANALISTA DE IMPUESTOS
A92: 10105 | B92: ALEXANDRE NAVARRETE GONZALEZ | D92: NAGA9207036R4 | E92: ANA MARIA DEL CARMEN VERTIZ ESTEVEZ | F92: DIRECCION | G92: CONTROL INTERNO | H92: ADMINISTRATIVO | I92: 19 | J92: 46188 | L92: =IF($B92="","",IFERROR(_xlfn.XLOOKUP(_xlfn.TEXTJOIN(" ",TRUE,_xlfn._xlws.SORT(_xlfn.TEXTSPLIT(TRIM(UPPER($B92))," ",,TRUE),1,1,TRUE)),puestos!$C$2:$C$324,puestos!$B$2:$B$324),"SIN PUESTO")) -> ESPECIALISTA CONTROL INTERNO
A93: 10108 | B93: SEBASTIAN RICOY CARRASCO | C93: sricoy@cafepuntadelcielo.co | D93: RICS990902KMA | E93: ESAU RAMIREZ CABALLERO | F93: LEGAL | G93: JURIDICO | H93: ADMINISTRATIVO | I93: 40 | J93: 46188 | L93: =IF($B93="","",IFERROR(_xlfn.XLOOKUP(_xlfn.TEXTJOIN(" ",TRUE,_xlfn._xlws.SORT(_xlfn.TEXTSPLIT(TRIM(UPPER($B93))," ",,TRUE),1,1,TRUE)),puestos!$C$2:$C$324,puestos!$B$2:$B$324),"SIN PUESTO")) -> ANALISTA DE LEGAL
A94: 10109 | B94: MARCELA CHACON LOPEZ | C94: mlopez@cafepuntadelcielo.co | D94: CALM930222UQ3 | E94: ERIKA GARCIA ROMAN | F94: COMPRAS | G94: COMPRAS | H94: ADMINISTRATIVO | I94: 78 | J94: 46188 | L94: =IF($B94="","",IFERROR(_xlfn.XLOOKUP(_xlfn.TEXTJOIN(" ",TRUE,_xlfn._xlws.SORT(_xlfn.TEXTSPLIT(TRIM(UPPER($B94))," ",,TRUE),1,1,TRUE)),puestos!$C$2:$C$324,puestos!$B$2:$B$324),"SIN PUESTO")) -> ESPECIALISTA DE COMPRAS
A95: 10110 | B95: ABRAHAM ISAIAS PADRON CASTRO | C95: apadron@biafoods.com | D95: PACA7802232G2 | E95: CARLOS ARTURO RODRIGUEZ MARCIA | F95: LOGISTICA & OPERACIONES | G95: LOGISTICA | H95: ADMINISTRATIVO | I95: 34 | J95: 46174 | L95: =IF($B95="","",IFERROR(_xlfn.XLOOKUP(_xlfn.TEXTJOIN(" ",TRUE,_xlfn._xlws.SORT(_xlfn.TEXTSPLIT(TRIM(UPPER($B95))," ",,TRUE),1,1,TRUE)),puestos!$C$2:$C$324,puestos!$B$2:$B$324),"SIN PUESTO")) -> DIRECTOR DE SUPPLY CHAIN
A96: 20001 | B96: MA GUADALUPE CORTEZ GONZALEZ | D96: COGG731229Q84 | E96: ODEMARIS LETICIA CUAMATZI RODRIGUEZ | F96: MANUFACTURA | G96: CALIDAD | H96: OPERATIVO | I96: 33 | J96: 04/09/2014 | L96: =IF($B96="","",IFERROR(_xlfn.XLOOKUP(_xlfn.TEXTJOIN(" ",TRUE,_xlfn._xlws.SORT(_xlfn.TEXTSPLIT(TRIM(UPPER($B96))," ",,TRUE),1,1,TRUE)),puestos!$C$2:$C$324,puestos!$B$2:$B$324),"SIN PUESTO")) -> INSPECTOR DE CALIDAD
A97: 20002 | B97: RICARDO MUÑOZ TAPIA | D97: MUTR870403AE6 | E97: EDUARDO DANIEL PONCE NAVARRO | F97: MANUFACTURA | G97: MANTENIMIENTO | H97: OPERATIVO | I97: 20 | J97: 08/09/2014 | L97: =IF($B97="","",IFERROR(_xlfn.XLOOKUP(_xlfn.TEXTJOIN(" ",TRUE,_xlfn._xlws.SORT(_xlfn.TEXTSPLIT(TRIM(UPPER($B97))," ",,TRUE),1,1,TRUE)),puestos!$C$2:$C$324,puestos!$B$2:$B$324),"SIN PUESTO")) -> COORDINADOR DE MANTENIMIENTO
A98: 20003 | B98: IXCHEL MAGALI PEREZ GONZALEZ | D98: PEGI930119BE3 | E98: ALMA DELIA HERRERA VAZQUEZ | F98: MANUFACTURA | G98: ADMINISTRACION PLANTA | H98: OPERATIVO | I98: 38 | J98: 08/09/2014 | L98: =IF($B98="","",IFERROR(_xlfn.XLOOKUP(_xlfn.TEXTJOIN(" ",TRUE,_xlfn._xlws.SORT(_xlfn.TEXTSPLIT(TRIM(UPPER($B98))," ",,TRUE),1,1,TRUE)),puestos!$C$2:$C$324,puestos!$B$2:$B$324),"SIN PUESTO")) -> COORDINADOR DE PRODUCCION
A99: 20004 | B99: SANDRA GONZALEZ HERNANDEZ | D99: GOHS730703M4A | E99: ODEMARIS LETICIA CUAMATZI RODRIGUEZ | F99: MANUFACTURA | G99: CALIDAD | H99: OPERATIVO | I99: 36 | J99: 21/11/2014 | L99: =IF($B99="","",IFERROR(_xlfn.XLOOKUP(_xlfn.TEXTJOIN(" ",TRUE,_xlfn._xlws.SORT(_xlfn.TEXTSPLIT(TRIM(UPPER($B99))," ",,TRUE),1,1,TRUE)),puestos!$C$2:$C$324,puestos!$B$2:$B$324),"SIN PUESTO")) -> INSPECTOR DE CALIDAD
A100: 20005 | B100: LUZ MARIA RODRIGUEZ GARRIDO | C100: lgarrido@cafepuntadelcielo.co | D100: ROGL770520LB4 | E100: ARMANDO RODRIGUEZ NAVARRETE | F100: MANUFACTURA | G100: COSTOS | H100: ADMINISTRATIVO | I100: 34 | J100: 08/06/2015 | L100: =IF($B100="","",IFERROR(_xlfn.XLOOKUP(_xlfn.TEXTJOIN(" ",TRUE,_xlfn._xlws.SORT(_xlfn.TEXTSPLIT(TRIM(UPPER($B100))," ",,TRUE),1,1,TRUE)),puestos!$C$2:$C$324,puestos!$B$2:$B$324),"SIN PUESTO")) -> ANALISTA DE COSTOS
...

Sheet puestos
A1: NOMBRE COMPLETO | B1: HOMOLOGACIÓN | C1: CLAVE
A2: GUTIERREZ VITE AUGUSTO ALONSO | B2: COORDINADOR ADMINISTRATIVO TRADE | C2: =IF(A2="","",_xlfn.TEXTJOIN(" ",TRUE,_xlfn._xlws.SORT(_xlfn.TEXTSPLIT(TRIM(UPPER(A2))," ",,TRUE),1,1,TRUE))) -> ALONSO AUGUSTO GUTIERREZ VITE
A3: HERRERA CRUZ ALEJANDRO | B3: CPFR | C3: =IF(A3="","",_xlfn.TEXTJOIN(" ",TRUE,_xlfn._xlws.SORT(_xlfn.TEXTSPLIT(TRIM(UPPER(A3))," ",,TRUE),1,1,TRUE))) -> ALEJANDRO CRUZ HERRERA
A4: GOMEZ REYES RICARDO EMANUEL | B4: CPFR | C4: =IF(A4="","",_xlfn.TEXTJOIN(" ",TRUE,_xlfn._xlws.SORT(_xlfn.TEXTSPLIT(TRIM(UPPER(A4))," ",,TRUE),1,1,TRUE))) -> EMANUEL GOMEZ REYES RICARDO
A5: LOPEZ PALLARES ELIZABETH | B5: EJECUTIVO DE FOOD SERVICE | C5: =IF(A5="","",_xlfn.TEXTJOIN(" ",TRUE,_xlfn._xlws.SORT(_xlfn.TEXTSPLIT(TRIM(UPPER(A5))," ",,TRUE),1,1,TRUE))) -> ELIZABETH LOPEZ PALLARES
A6: ESCALONA MEXICA NANCY | B6: ESPECIALISTA DE OBZ COMERCIAL | C6: =IF(A6="","",_xlfn.TEXTJOIN(" ",TRUE,_xlfn._xlws.SORT(_xlfn.TEXTSPLIT(TRIM(UPPER(A6))," ",,TRUE),1,1,TRUE))) -> ESCALONA MEXICA NANCY
A7: JIMENEZ UGALDE JORGE ANTONIO | B7: GERENTE COMERCIAL | C7: =IF(A7="","",_xlfn.TEXTJOIN(" ",TRUE,_xlfn._xlws.SORT(_xlfn.TEXTSPLIT(TRIM(UPPER(A7))," ",,TRUE),1,1,TRUE))) -> ANTONIO JIMENEZ JORGE UGALDE
A8: CORTES CAZAREZ FELIPE | B8: GERENTE TRADE MARKETING | C8: =IF(A8="","",_xlfn.TEXTJOIN(" ",TRUE,_xlfn._xlws.SORT(_xlfn.TEXTSPLIT(TRIM(UPPER(A8))," ",,TRUE),1,1,TRUE))) -> CAZAREZ CORTES FELIPE
A9: SILVA SANTIAGO ARTURO | B9: KAM MAYOREO Y DISTRIBUIDORES | C9: =IF(A9="","",_xlfn.TEXTJOIN(" ",TRUE,_xlfn._xlws.SORT(_xlfn.TEXTSPLIT(TRIM(UPPER(A9))," ",,TRUE),1,1,TRUE))) -> ARTURO SANTIAGO SILVA
A10: LOPEZ HIDROGO PAULA | B10: KAM NORTE | C10: =IF(A10="","",_xlfn.TEXTJOIN(" ",TRUE,_xlfn._xlws.SORT(_xlfn.TEXTSPLIT(TRIM(UPPER(A10))," ",,TRUE),1,1,TRUE))) -> HIDROGO LOPEZ PAULA
A11: VALENZUELA LOPEZ MAURICIO EDUARDO | B11: KAM VALLE DE MEXICO | C11: =IF(A11="","",_xlfn.TEXTJOIN(" ",TRUE,_xlfn._xlws.SORT(_xlfn.TEXTSPLIT(TRIM(UPPER(A11))," ",,TRUE),1,1,TRUE))) -> EDUARDO LOPEZ MAURICIO VALENZUELA
A12: MEDINA CRUZ FERNANDO | B12: PROMOTOR DE VENTAS | C12: =IF(A12="","",_xlfn.TEXTJOIN(" ",TRUE,_xlfn._xlws.SORT(_xlfn.TEXTSPLIT(TRIM(UPPER(A12))," ",,TRUE),1,1,TRUE))) -> CRUZ FERNANDO MEDINA
A13: ALAMILLA LOPEZ MARGARITA | B13: PROMOTOR DE VENTAS | C13: =IF(A13="","",_xlfn.TEXTJOIN(" ",TRUE,_xlfn._xlws.SORT(_xlfn.TEXTSPLIT(TRIM(UPPER(A13))," ",,TRUE),1,1,TRUE))) -> ALAMILLA LOPEZ MARGARITA
... A324: QUEZADA MENDEZ EDUARDO DANIEL | B324: GERENTE DE REVENUE / BI | C324: =IF(A324="","",_xlfn.TEXTJOIN(" ",TRUE,_xlfn._xlws.SORT(_xlfn.TEXTSPLIT(TRIM(UPPER(A324))," ",,TRUE),1,1,TRUE))) -> DANIEL EDUARDO MENDEZ QUEZADA
